README.txt
setup.py
varlock_throw/__init__.py
varlock_throw/__main__.py
varlock_throw.egg-info/PKG-INFO
varlock_throw.egg-info/SOURCES.txt
varlock_throw.egg-info/dependency_links.txt
varlock_throw.egg-info/requires.txt
varlock_throw.egg-info/top_level.txt