Metadata-Version: 1.1
Name: varlock-throw
Version: 0.0.4
Summary: funtion to return scambled list of word when a list of word is inputed
Home-page: UNKNOWN
Author: Varun Dineshan
Author-email: cc2164@gmail.com
License: MIT
Keywords: scramble
Platform: UNKNOWN
Classifier: Development Status :: 5 - Production/Stable
Classifier: Intended Audience :: Education
Classifier: Operating System :: Microsoft :: Windows :: Windows 10
Classifier: License :: OSI Approved :: MIT License
Classifier: Programming Language :: Python :: 3.7
